RsCMPX_LteMeas/RsCMPX_LteMeas.py
RsCMPX_LteMeas/__init__.py
RsCMPX_LteMeas/enums.py
RsCMPX_LteMeas/py.typed.py
RsCMPX_LteMeas/repcap.py
RsCMPX_LteMeas/CustomFiles/__init__.py
RsCMPX_LteMeas/CustomFiles/events.py
RsCMPX_LteMeas/CustomFiles/reliability.py
RsCMPX_LteMeas/CustomFiles/utilities.py
RsCMPX_LteMeas/Implementations/__init__.py
RsCMPX_LteMeas/Implementations/Catalog/__init__.py
RsCMPX_LteMeas/Implementations/Catalog/LteMeas/Spath.py
RsCMPX_LteMeas/Implementations/Catalog/LteMeas/__init__.py
RsCMPX_LteMeas/Implementations/Configure/__init__.py
RsCMPX_LteMeas/Implementations/Configure/LteMeas/Emtc.py
RsCMPX_LteMeas/Implementations/Configure/LteMeas/Network.py
RsCMPX_LteMeas/Implementations/Configure/LteMeas/Pcc.py
RsCMPX_LteMeas/Implementations/Configure/LteMeas/__init__.py
RsCMPX_LteMeas/Implementations/Configure/LteMeas/CarrierAggregation/ChannelBw.py
RsCMPX_LteMeas/Implementations/Configure/LteMeas/CarrierAggregation/Mcarrier.py
RsCMPX_LteMeas/Implementations/Configure/LteMeas/CarrierAggregation/Mode.py
RsCMPX_LteMeas/Implementations/Configure/LteMeas/CarrierAggregation/__init__.py
RsCMPX_LteMeas/Implementations/Configure/LteMeas/CarrierAggregation/Frequency/Aggregated.py
RsCMPX_LteMeas/Implementations/Configure/LteMeas/CarrierAggregation/Frequency/__init__.py
RsCMPX_LteMeas/Implementations/Configure/LteMeas/CarrierAggregation/Maping/Scc.py
RsCMPX_LteMeas/Implementations/Configure/LteMeas/CarrierAggregation/Maping/__init__.py
RsCMPX_LteMeas/Implementations/Configure/LteMeas/CarrierAggregation/Scc/AcSpacing.py
RsCMPX_LteMeas/Implementations/Configure/LteMeas/CarrierAggregation/Scc/__init__.py
RsCMPX_LteMeas/Implementations/Configure/LteMeas/Cc/ChannelBw.py
RsCMPX_LteMeas/Implementations/Configure/LteMeas/Cc/__init__.py
RsCMPX_LteMeas/Implementations/Configure/LteMeas/MultiEval/MsubFrames.py
RsCMPX_LteMeas/Implementations/Configure/LteMeas/MultiEval/NsValue.py
RsCMPX_LteMeas/Implementations/Configure/LteMeas/MultiEval/Pcc.py
rscmpx_ltemeas-6.0.61.dist-info/METADATA
rscmpx_ltemeas-6.0.61.dist-info/WHEEL
rscmpx_ltemeas-6.0.61.dist-info/top_level.txt
rscmpx_ltemeas-6.0.61.dist-info/RECORD
