Metadata-Version: 2.4
Name: RsCMPX_LteMeas
Version: 6.0.61
Summary: CMX/CMP LTE Measurement Remote-control module
Author: Rohde & Schwarz GmbH & Co. KG
Maintainer: Rohde & Schwarz GmbH & Co. KG
License-Expression: MIT
Project-URL: Documentation, https://RsCMPX-LteMeas.readthedocs.io/
Project-URL: Examples, https://github.com/Rohde-Schwarz/Examples/
Keywords: CMP,CMP180,CMX,PVT
Classifier: Development Status :: 5 - Production/Stable
Classifier: Intended Audience :: Developers
Classifier: Programming Language :: Python :: 3
Classifier: Programming Language :: Python :: 3.8
Classifier: Programming Language :: Python :: 3.9
Classifier: Programming Language :: Python :: 3.10
Classifier: Programming Language :: Python :: 3.11
Classifier: Programming Language :: Python :: 3.12
Classifier: Programming Language :: Python :: 3.13
Requires-Python: >=3.8
Requires-Dist: pyvisa>=1.13.0
Requires-Dist: typing-extensions>=4.0.0
